qufit/__init__.py
qufit/auxfile.py
qufit/dataTools.py
qufit/math.py
qufit/netdatatrans.py
qufit/opt.py
qufit/opt_new.py
qufit/optimize.py
qufit/plot.py
qufit/qubit.py
qufit-1.1.70.dist-info/METADATA
qufit-1.1.70.dist-info/WHEEL
qufit-1.1.70.dist-info/top_level.txt
qufit-1.1.70.dist-info/RECORD
