Metadata-Version: 2.1
Name: qufit
Version: 1.1.70
Summary: 本模块包括了超导量子计算实验中常用模型的拟合函数于数据处理方法。
Home-page: https://pypi.org/
Author: 赵寿宽(sk zhao)
Author-email: 2396776980@qq.com
Classifier: Programming Language :: Python :: 3
Classifier: License :: OSI Approved :: MIT License
Classifier: Operating System :: Microsoft :: Windows
